<?xml version="1.0"?>
<!DOCTYPE hibernate-mapping PUBLIC "-//Hibernate/Hibernate Mapping DTD 3.0//EN"
"http://hibernate.sourceforge.net/hibernate-mapping-3.0.dtd">
<!-- Generated 05/02/2014 14:26:05 by Hibernate Tools 3.2.1.GA -->
<hibernate-mapping>
    <class name="Modelo.Repuesto" table="repuesto" catalog="seminario">
        <id name="idrepuesto" type="java.lang.Integer">
            <column name="idrepuesto" />
            <generator class="identity" />
        </id>
        <property name="nombre" type="string">
            <column name="nombre" length="65535" not-null="true" />
        </property>
        <property name="stock" type="int">
            <column name="stock" not-null="true" />
        </property>
        <set name="provrepuestos" inverse="true">
            <key>
                <column name="repuesto_id" not-null="true" />
            </key>
            <one-to-many class="Modelo.Provrepuesto" />
        </set>
    </class>
</hibernate-mapping>
